{
    "asset": 2272000000,
    "cancellation": "なし",
    "category": "バランス-国内・アクティブ",
    "compensation": 0.010422,
    "course": "口数・金額",
    "deadline": "15:00",
    "distribution": "年2回",
    "fee": 0,
    "fund_name": "ＪＰＭ−ＪＰＭ日本債券アルファ（愛称：日本の一九)",
    "id": "17311093",
    "modified": 1424096036,
    "modified_str": "2015-02-16 14:13:56",
    "policy": "日本債券と日本株式に分散投資します。日本債券と日本株式への基本資産配分比率は原則９０：１０とします。半年毎に決算を行い、分配金額を決定します。",
    "refund_date": "2019\/06\/10",
    "reservation_fee": "なし",
    "settlement_schedule": "約定日から3営業日後",
    "trade_schedule": "ご注文日の翌営業日（国内・海外の休場により遅れる場合がございます）",
    "type": "バランス型"
}