{
    "asset": 2390000000,
    "cancellation": "なし",
    "category": "新興国株式-アクティブ・アジア・中国",
    "compensation": 0.01674,
    "course": "口数・金額",
    "deadline": "15:00",
    "distribution": "年1回",
    "fee": 0,
    "fund_name": "損保Ｊ日本興亜−損保ジャパン拡大中国株投信",
    "id": "45311053",
    "modified": 1424098770,
    "modified_str": "2015-02-16 14:59:30",
    "policy": "主として「損保ジャパン拡大中国株マザーファンド」の受益証券への投資を通して、中国、香港及び台湾の株式（DR（預託証書）を含みます。）に投資し、信託財産の着実な成長と安定した収益の確保を目指します。",
    "refund_date": "無期限",
    "reservation_fee": 0.003,
    "settlement_schedule": "約定日から3営業日後",
    "trade_schedule": "ご注文日の翌営業日（国内・海外の休場により遅れる場合がございます）",
    "type": "新興国株式"
}