{
    "asset": 1393000000,
    "cancellation": "なし",
    "category": "海外株式-アクティブ・一般・水",
    "compensation": 0.01696,
    "course": "口数・金額",
    "deadline": "15:00",
    "distribution": "年1回",
    "fee": 0.0216,
    "fund_name": "日興−グローバルウォーターファンド",
    "id": "02311076",
    "modified": 1424050435,
    "modified_str": "2015-02-16 01:33:55",
    "policy": "水資源を支える世界各国の企業（＝水関連企業）の株式に分散投資を行ない、中長期的な信託財産の成長をめざします。投資信託証券に投資を行なうファンド・オブ・ファンズです。外貨建資産への投資にあたっては、原則として為替ヘッジは行ないません。",
    "refund_date": "2017\/06\/15",
    "reservation_fee": "なし",
    "settlement_schedule": "約定日から4営業日後",
    "trade_schedule": "ご注文日の翌営業日（国内・海外の休場により遅れる場合がございます）",
    "type": "海外株式"
}