{
    "asset": 18045000000,
    "cancellation": "なし",
    "category": "新興国株式-アクティブ・アジア・インド",
    "compensation": 0.0195,
    "course": "口数・金額",
    "deadline": "13:00",
    "distribution": "年1回",
    "fee": 0.0108,
    "fund_name": "ドイチェ−インド株式ファンド",
    "id": "3431104C",
    "modified": 1424095835,
    "modified_str": "2015-02-16 14:10:35",
    "policy": "主として円建ての外国投資信託であるドイチェ・インディア・エクイティ・ファンドおよび証券投資信託であるドイチェ・日本債券マザーの投資信託証券への投資を通じて、インドの証券取引所に上場されている株式等に実質的な投資を行い、信託財産の積極的な成長をめざして運用を行ないます。",
    "refund_date": "2024\/11\/29",
    "reservation_fee": 0.003,
    "settlement_schedule": "約定日から5営業日後",
    "trade_schedule": "ご注文日の翌営業日（国内・海外の休場により遅れる場合がございます）",
    "type": "新興国株式"
}